[
  {
    "protocol": "Aave",
    "chain": "Ethereum",
    "tvl": "1815.687009458601952371"
  },
  {
    "protocol": "Asymmetry",
    "chain": "Ethereum",
    "tvl": "-1"
  },
  {
    "protocol": "Compound",
    "chain": "Ethereum",
    "tvl": "539.908055592789867625"
  },
  {
    "protocol": "Curve",
    "chain": "Ethereum",
    "tvl": "1262.581461953078967156"
  },
  {
    "protocol": "Gearbox",
    "chain": "Ethereum",
    "tvl": "3.830323039969781655"
  },
  {
    "protocol": "Merkl",
    "chain": "Ethereum",
    "tvl": "-1"
  },
  {
    "protocol": "Spark/Maker",
    "chain": "Ethereum",
    "tvl": "22.544993060514585971"
  },
  {
    "protocol": "Uniswap",
    "chain": "Ethereum",
    "tvl": "144.164864829035663159"
  },
  {
    "protocol": "Yield Basis",
    "chain": "Ethereum",
    "tvl": "1073.127598034628792205"
  },
  {
    "protocol": "Aave",
    "chain": "Arbitrum",
    "tvl": "19.098634211402367104"
  },
  {
    "protocol": "Curve",
    "chain": "Arbitrum",
    "tvl": "23.06005127527837657"
  },
  {
    "protocol": "Nerite",
    "chain": "Arbitrum",
    "tvl": "-1"
  },
  {
    "protocol": "Uniswap",
    "chain": "Arbitrum",
    "tvl": "17.20696919864174153"
  },
  {
    "protocol": "Aave",
    "chain": "Base",
    "tvl": "10.847417759939459572"
  },
  {
    "protocol": "Aerodrome",
    "chain": "Base",
    "tvl": "4.18919055407327239"
  },
  {
    "protocol": "Curve",
    "chain": "Base",
    "tvl": "0.000000182232859193"
  },
  {
    "protocol": "Curve",
    "chain": "Optimism",
    "tvl": "1.525302193784842417"
  },
  {
    "protocol": "Uniswap",
    "chain": "Optimism",
    "tvl": "0.067709121751185197"
  },
  {
    "protocol": "Velodrome",
    "chain": "Optimism",
    "tvl": "6.219462746357191759"
  },
  {
    "protocol": "Ekubo",
    "chain": "Starknet",
    "tvl": "30.445987234010060489"
  },
  {
    "protocol": "Endur",
    "chain": "Starknet",
    "tvl": "20.460839641623185943"
  },
  {
    "protocol": "Vesu",
    "chain": "Starknet",
    "tvl": "25.780350790751391702"
  },
  {
    "protocol": "Starknet Earn",
    "chain": "Starknet",
    "tvl": "-1"
  },
  {
    "protocol": "0D",
    "chain": "Starknet",
    "tvl": "-1"
  },
  {
    "protocol": "AlphaLend",
    "chain": "Sui",
    "tvl": "53.8209007"
  },
  {
    "protocol": "Bluefin",
    "chain": "Sui",
    "tvl": "-1"
  },
  {
    "protocol": "Bucket",
    "chain": "Sui",
    "tvl": "0.00577132"
  },
  {
    "protocol": "Ember",
    "chain": "Sui",
    "tvl": "49.34089922"
  }
]