[
  {
    "protocol": "Aave",
    "chain": "Ethereum",
    "tvl": "2369.644017607276287703"
  },
  {
    "protocol": "Asymmetry",
    "chain": "Ethereum",
    "tvl": "-1"
  },
  {
    "protocol": "Compound",
    "chain": "Ethereum",
    "tvl": "374.762512817246654739"
  },
  {
    "protocol": "Curve",
    "chain": "Ethereum",
    "tvl": "-1"
  },
  {
    "protocol": "Gearbox",
    "chain": "Ethereum",
    "tvl": "-1"
  },
  {
    "protocol": "Merkl",
    "chain": "Ethereum",
    "tvl": "-1"
  },
  {
    "protocol": "Spark/Maker",
    "chain": "Ethereum",
    "tvl": "22.530657243030840442"
  },
  {
    "protocol": "Uniswap",
    "chain": "Ethereum",
    "tvl": "-1"
  },
  {
    "protocol": "Yield Basis",
    "chain": "Ethereum",
    "tvl": "-1"
  },
  {
    "protocol": "Aave",
    "chain": "Arbitrum",
    "tvl": "29.244570195774921813"
  },
  {
    "protocol": "Curve",
    "chain": "Arbitrum",
    "tvl": "8.15620657923428494"
  },
  {
    "protocol": "Nerite",
    "chain": "Arbitrum",
    "tvl": "-1"
  },
  {
    "protocol": "Uniswap",
    "chain": "Arbitrum",
    "tvl": "7.242198245837600605"
  },
  {
    "protocol": "Aave",
    "chain": "Base",
    "tvl": "8.440627816892390246"
  },
  {
    "protocol": "Aerodrome",
    "chain": "Base",
    "tvl": "5.022127005021494224"
  },
  {
    "protocol": "Curve",
    "chain": "Base",
    "tvl": "0"
  },
  {
    "protocol": "Curve",
    "chain": "Optimism",
    "tvl": "1.345616929620707391"
  },
  {
    "protocol": "Uniswap",
    "chain": "Optimism",
    "tvl": "0.360646999942176476"
  },
  {
    "protocol": "Velodrome",
    "chain": "Optimism",
    "tvl": "4.412952127891748223"
  },
  {
    "protocol": "Ekubo",
    "chain": "Starknet",
    "tvl": "43.295389540647256501"
  },
  {
    "protocol": "Endur",
    "chain": "Starknet",
    "tvl": "11.692412785177614718"
  },
  {
    "protocol": "Vesu",
    "chain": "Starknet",
    "tvl": "21.917249448647896135"
  },
  {
    "protocol": "Starknet Earn",
    "chain": "Starknet",
    "tvl": "-1"
  },
  {
    "protocol": "0D",
    "chain": "Starknet",
    "tvl": "-1"
  },
  {
    "protocol": "AlphaLend",
    "chain": "Sui",
    "tvl": "50.47117684"
  },
  {
    "protocol": "Bluefin",
    "chain": "Sui",
    "tvl": "-1"
  },
  {
    "protocol": "Bucket",
    "chain": "Sui",
    "tvl": "0.00577132"
  },
  {
    "protocol": "Ember",
    "chain": "Sui",
    "tvl": "41.82521592"
  }
]