[
  {
    "protocol": "Aave",
    "chain": "Ethereum",
    "tvl": "1824.697747021489330793"
  },
  {
    "protocol": "Asymmetry",
    "chain": "Ethereum",
    "tvl": "-1"
  },
  {
    "protocol": "Compound",
    "chain": "Ethereum",
    "tvl": "539.718055592789867625"
  },
  {
    "protocol": "Curve",
    "chain": "Ethereum",
    "tvl": "1227.497413062156360522"
  },
  {
    "protocol": "Gearbox",
    "chain": "Ethereum",
    "tvl": "3.830337524837543564"
  },
  {
    "protocol": "Merkl",
    "chain": "Ethereum",
    "tvl": "-1"
  },
  {
    "protocol": "Spark/Maker",
    "chain": "Ethereum",
    "tvl": "22.544993060514585971"
  },
  {
    "protocol": "Uniswap",
    "chain": "Ethereum",
    "tvl": "159.17090531173058351"
  },
  {
    "protocol": "Yield Basis",
    "chain": "Ethereum",
    "tvl": "1042.048070885456041756"
  },
  {
    "protocol": "Aave",
    "chain": "Arbitrum",
    "tvl": "19.102231241402367104"
  },
  {
    "protocol": "Curve",
    "chain": "Arbitrum",
    "tvl": "22.34678317807707993"
  },
  {
    "protocol": "Nerite",
    "chain": "Arbitrum",
    "tvl": "-1"
  },
  {
    "protocol": "Uniswap",
    "chain": "Arbitrum",
    "tvl": "16.637159220755816097"
  },
  {
    "protocol": "Aave",
    "chain": "Base",
    "tvl": "11.046145039151626634"
  },
  {
    "protocol": "Aerodrome",
    "chain": "Base",
    "tvl": "6.549480986568951597"
  },
  {
    "protocol": "Curve",
    "chain": "Base",
    "tvl": "0.000000182232859193"
  },
  {
    "protocol": "Curve",
    "chain": "Optimism",
    "tvl": "1.516294680602976225"
  },
  {
    "protocol": "Uniswap",
    "chain": "Optimism",
    "tvl": "0.078561457285442215"
  },
  {
    "protocol": "Velodrome",
    "chain": "Optimism",
    "tvl": "6.521169664296800666"
  },
  {
    "protocol": "Ekubo",
    "chain": "Starknet",
    "tvl": "30.041749279462757181"
  },
  {
    "protocol": "Endur",
    "chain": "Starknet",
    "tvl": "20.462781486932102852"
  },
  {
    "protocol": "Vesu",
    "chain": "Starknet",
    "tvl": "25.782610682793375841"
  },
  {
    "protocol": "Starknet Earn",
    "chain": "Starknet",
    "tvl": "-1"
  },
  {
    "protocol": "0D",
    "chain": "Starknet",
    "tvl": "-1"
  },
  {
    "protocol": "AlphaLend",
    "chain": "Sui",
    "tvl": "53.08429789"
  },
  {
    "protocol": "Bluefin",
    "chain": "Sui",
    "tvl": "-1"
  },
  {
    "protocol": "Bucket",
    "chain": "Sui",
    "tvl": "0.00577132"
  },
  {
    "protocol": "Ember",
    "chain": "Sui",
    "tvl": "49.35594344"
  }
]